unicodeart/__init__.py
unicodeart/config.txt
unicodeart/console.py
unicodeart/cprint.py
unicodeart/global_vars.py
unicodeart/output.txt
unicodeart/unicodeart_util.py
unicodeart-0.0.5.dist-info/METADATA
unicodeart-0.0.5.dist-info/WHEEL
unicodeart-0.0.5.dist-info/licenses/LICENSE
unicodeart-0.0.5.dist-info/RECORD
