Metadata-Version: 2.1
Name: unicodeart
Version: 0.0.5
Summary: unicode art tool
Project-URL: Homepage, https://github.com/mandolin/UnicodeArt
Project-URL: Issues, https://github.com/mandolin/UnicodeArt/issues
Author-email: mandolin2099 <mandolin.mdy@gmail.com>
License-File: LICENSE
Classifier: License :: OSI Approved :: GNU General Public License v3 (GPLv3)
Classifier: Operating System :: OS Independent
Classifier: Programming Language :: Python :: 3
Requires-Python: >=3.8
